flake8_eol.py
flake8_eol-0.0.8.dist-info/METADATA
flake8_eol-0.0.8.dist-info/WHEEL
flake8_eol-0.0.8.dist-info/entry_points.txt
flake8_eol-0.0.8.dist-info/top_level.txt
flake8_eol-0.0.8.dist-info/RECORD
