Metadata-Version: 2.1
Name: flake8-eol
Version: 0.0.8
Summary: Flake8 plugin to enforce Unix/Linux EOL consistency
Author: Claudio Scheer
Author-email: claudioscheer@protonmail.com
Classifier: Framework :: Flake8
Classifier: Environment :: Console
Classifier: Intended Audience :: Developers
Classifier: Programming Language :: Python :: 3
Classifier: Programming Language :: Python :: 3.8
Classifier: Programming Language :: Python
Classifier: Topic :: Software Development :: Libraries :: Python Modules
Classifier: Topic :: Software Development :: Quality Assurance
Requires-Python: >=3.8
Requires-Dist: flake8 (>=3.7.0)
